instanthost.py
instanthost-1.1.dist-info/LICENSE
instanthost-1.1.dist-info/METADATA
instanthost-1.1.dist-info/WHEEL
instanthost-1.1.dist-info/entry_points.txt
instanthost-1.1.dist-info/top_level.txt
instanthost-1.1.dist-info/RECORD
