Metadata-Version: 2.1
Name: instanthost
Version: 1.1
Summary: A cli tool to host any non-binary files
Home-page: https://github.com/yogeshwaran01/Instant-Host
Author: Yogeshwaran R
Author-email: yogeshin247@gmail.com
License: MIT
Download-URL: https://raw.githubusercontent.com/yogeshwaran01/Instant-Host/master/instanthost.py
Platform: UNKNOWN
Classifier: Programming Language :: Python :: 3
Classifier: License :: OSI Approved :: MIT License
Classifier: Operating System :: OS Independent
